[
    {
        "team": "India",
        "batsman": "MS Dhoni (c) †",
        "runs": "6",
        "balls": "11",
        "SR": "54.54"
    },
    {
        "team": "India",
        "batsman": "MS Dhoni (c) †",
        "runs": "85",
        "balls": "76",
        "SR": "111.84"
    },
    {
        "team": "India",
        "batsman": "MS Dhoni (c) †",
        "runs": "18",
        "balls": "11",
        "SR": "163.63"
    },
    {
        "team": "India",
        "batsman": "MS Dhoni (c) †",
        "runs": "65",
        "balls": "65",
        "SR": "100.00"
    },
    {
        "team": "India",
        "batsman": "MS Dhoni (c) †",
        "runs": "18",
        "balls": "13",
        "SR": "138.46"
    },
    {
        "team": "India",
        "batsman": "MS Dhoni (c) †",
        "runs": "45",
        "balls": "56",
        "SR": "80.35"
    }
]